groundwork_database/__init__.py
groundwork_database/version.py
groundwork_database/patterns/__init__.py
groundwork_database/patterns/gw_sql_pattern.py
groundwork_database/plugins/__init__.py
groundwork_database/plugins/gwdatabase_plugin.py
tests/test_plugins/__init__.py
tests/test_plugins/database_plugin.py
tests/test_plugins/empty_database_plugin.py
groundwork_database-0.1.3.dist-info/top_level.txt
groundwork_database-0.1.3.dist-info/entry_points.txt
groundwork_database-0.1.3.dist-info/METADATA
groundwork_database-0.1.3.dist-info/DESCRIPTION.rst
groundwork_database-0.1.3.dist-info/metadata.json
groundwork_database-0.1.3.dist-info/WHEEL
groundwork_database-0.1.3.dist-info/RECORD
